{
  "project_info": {
    "project_number": "594899742468",
    "firebase_url": "https://tetststst-a1360-default-rtdb.firebaseio.com",
    "project_id": "tetststst-a1360",
    "storage_bucket": "tetststst-a1360.appspot.com"
  },
  "client": [
    {
      "client_info": {
        "mobilesdk_app_id": "1:594899742468:android:e71ca876f93bf949046a51",
        "android_client_info": {
          "package_name": "com.example.real_time_geriatric_health_care_system"
        }
      },
      "oauth_client": [
        {
          "client_id": "594899742468-2pm1sgfrihtsetvfinoglk85jq72pfh4.apps.googleusercontent.com",
          "client_type": 1,
          "android_info": {
            "package_name": "com.example.real_time_geriatric_health_care_system",
            "certificate_hash": "be0d814ad85f60df7b282fa974be563c619e578e"
          }
        },
        {
          "client_id": "594899742468-bun67j0dnvnmja7vd9nclum0194k80s3.apps.googleusercontent.com",
          "client_type": 3
        }
      ],
      "api_key": [
        {
          "current_key": "AIzaSyAHKRu3i4gZrdhpKKuNNY33xtTfPF64IWg"
        }
      ],
      "services": {
        "appinvite_service": {
          "other_platform_oauth_client": [
            {
              "client_id": "594899742468-bun67j0dnvnmja7vd9nclum0194k80s3.apps.googleusercontent.com",
              "client_type": 3
            },
            {
              "client_id": "594899742468-ulminbf2914k882q7h0g9euv4f468tde.apps.googleusercontent.com",
              "client_type": 2,
              "ios_info": {
                "bundle_id": "com.example.realTimeGeriatricHealthCareSystem"
              }
            }
          ]
        }
      }
    }
  ],
  "configuration_version": "1"
}